pipelex/__init__.py
pipelex/base_exceptions.py
pipelex/config.py
pipelex/exceptions.py
pipelex/hub.py
pipelex/pipelex.py
pipelex/pipelex.toml
pipelex/py.typed
pipelex/types.py
pipelex/urls.py
pipelex/builder/__init__.py
pipelex/builder/builder.plx
pipelex/builder/builder.py
pipelex/builder/builder_errors.py
pipelex/builder/builder_loop.py
pipelex/builder/bundle_header_spec.py
pipelex/builder/bundle_spec.py
pipelex/builder/exceptions.py
pipelex/builder/flow.py
pipelex/builder/flow_factory.py
pipelex/builder/runner_code.py
pipelex/builder/concept/__init__.py
pipelex/builder/concept/concept_spec.py
pipelex/builder/pipe/__init__.py
pipelex/builder/pipe/pipe_batch_spec.py
pipelex/builder/pipe/pipe_compose_spec.py
pipelex/builder/pipe/pipe_condition_spec.py
pipelex/builder/pipe/pipe_design.plx
pipelex/builder/pipe/pipe_extract_spec.py
pipelex/builder/pipe/pipe_func_spec.py
pipelex/builder/pipe/pipe_img_gen_spec.py
pipelex/builder/pipe/pipe_llm_spec.py
pipelex/builder/pipe/pipe_parallel_spec.py
pipelex/builder/pipe/pipe_sequence_spec.py
pipelex/builder/pipe/pipe_signature.py
pipelex/builder/pipe/pipe_spec.py
pipelex/builder/pipe/pipe_spec_map.py
pipelex/builder/pipe/pipe_spec_union.py
pipelex/builder/pipe/sub_pipe_spec.py
pipelex/cli/__init__.py
pipelex/cli/_cli.py
pipelex/cli/error_handlers.py
pipelex/cli/exceptions.py
pipelex/cli/readiness.py
pipelex/cli/commands/__init__.py
pipelex/cli/commands/build_cmd.py
pipelex/cli/commands/doctor_cmd.py
pipelex/cli/commands/kit_cmd.py
pipelex/cli/commands/run_cmd.py
pipelex/cli/commands/show_cmd.py
pipelex/cli/commands/validate_cmd.py
pipelex/cli/commands/init/__init__.py
pipelex/cli/commands/init/backends.py
pipelex/cli/commands/init/command.py
pipelex/cli/commands/init/config_files.py
pipelex/cli/commands/init/routing.py
pipelex/cli/commands/init/telemetry.py
pipelex/cli/commands/init/ui/__init__.py
pipelex/cli/commands/init/ui/backends_ui.py
pipelex/cli/commands/init/ui/general_ui.py
pipelex/cli/commands/init/ui/routing_ui.py
pipelex-0.17.5.dist-info/METADATA
pipelex-0.17.5.dist-info/WHEEL
pipelex-0.17.5.dist-info/entry_points.txt
pipelex-0.17.5.dist-info/licenses/LICENSE
pipelex-0.17.5.dist-info/RECORD
