Metadata-Version: 2.4
Name: pipelex
Version: 0.17.5
Summary: The open standard for repeatable AI workflows. Write business logic, not API calls.
Project-URL: Homepage, https://pipelex.com
Project-URL: Repository, https://github.com/Pipelex/pipelex
Project-URL: Documentation, https://docs.pipelex.com/
Project-URL: Changelog, https://docs.pipelex.com/changelog/
Author-email: "Evotis S.A.S." <oss@pipelex.com>
Maintainer-email: Pipelex staff <oss@pipelex.com>
License-Expression: MIT
License-File: LICENSE
Classifier: License :: OSI Approved :: MIT License
Classifier: Operating System :: OS Independent
Classifier: Programming Language :: Python :: 3
Classifier: Programming Language :: Python :: 3.10
Classifier: Programming Language :: Python :: 3.11
Classifier: Programming Language :: Python :: 3.12
Classifier: Programming Language :: Python :: 3.13
Requires-Python: <3.14,>=3.10
Requires-Dist: aiofiles>=23.2.1
Requires-Dist: backports-strenum>=1.3.0; python_version < '3.11'
Requires-Dist: filetype>=1.2.0
Requires-Dist: httpx<1.0.0,>=0.23.0
Requires-Dist: instructor!=1.11.*,!=1.12.*,>=1.8.3
Requires-Dist: jinja2>=3.1.4
Requires-Dist: json2html>=1.3.0
Requires-Dist: kajson==0.3.1
Requires-Dist: markdown>=3.6
Requires-Dist: networkx>=3.4.2
Requires-Dist: openai>=1.108.1
Requires-Dist: pillow>=11.2.1
Requires-Dist: polyfactory>=2.21.0
Requires-Dist: posthog>=6.7.0
Requires-Dist: pydantic<3.0.0,>=2.10.6
Requires-Dist: pypdfium2!=4.30.1,>=4.30.0
Requires-Dist: python-dotenv>=1.0.1
Requires-Dist: pyyaml>=6.0.2
Requires-Dist: rich>=13.8.1
Requires-Dist: shortuuid>=1.0.13
Requires-Dist: tomli>=2.3.0
Requires-Dist: tomlkit>=0.13.2
Requires-Dist: typer>=0.16.0
Requires-Dist: typing-extensions>=4.13.2
Requires-Dist: yattag>=1.15.2
Provides-Extra: anthropic
Requires-Dist: anthropic>=0.60.0; extra == 'anthropic'
Provides-Extra: bedrock
Requires-Dist: aioboto3>=13.4.0; extra == 'bedrock'
Requires-Dist: boto3>=1.34.131; extra == 'bedrock'
Provides-Extra: dev
Requires-Dist: boto3-stubs>=1.35.24; extra == 'dev'
Requires-Dist: mypy>=1.11.2; extra == 'dev'
Requires-Dist: pylint>=3.3.8; extra == 'dev'
Requires-Dist: pyright>=1.1.405; extra == 'dev'
Requires-Dist: pytest-asyncio>=0.24.0; extra == 'dev'
Requires-Dist: pytest-cov>=6.1.1; extra == 'dev'
Requires-Dist: pytest-mock>=3.14.0; extra == 'dev'
Requires-Dist: pytest-sugar>=1.0.0; extra == 'dev'
Requires-Dist: pytest-xdist>=3.6.1; extra == 'dev'
Requires-Dist: pytest>=9.0.1; extra == 'dev'
Requires-Dist: ruff>=0.6.8; extra == 'dev'
Requires-Dist: types-aioboto3[bedrock,bedrock-runtime]>=13.4.0; extra == 'dev'
Requires-Dist: types-aiofiles>=24.1.0.20240626; extra == 'dev'
Requires-Dist: types-markdown>=3.6.0.20240316; extra == 'dev'
Requires-Dist: types-networkx>=3.3.0.20241020; extra == 'dev'
Requires-Dist: types-pyyaml>=6.0.12.20250326; extra == 'dev'
Provides-Extra: docs
Requires-Dist: mike>=2.1.3; extra == 'docs'
Requires-Dist: mkdocs-glightbox>=0.4.0; extra == 'docs'
Requires-Dist: mkdocs-material>=9.6.14; extra == 'docs'
Requires-Dist: mkdocs-meta-manager>=1.1.0; extra == 'docs'
Requires-Dist: mkdocs>=1.6.1; extra == 'docs'
Provides-Extra: fal
Requires-Dist: fal-client>=0.4.1; extra == 'fal'
Provides-Extra: google
Requires-Dist: google-auth-oauthlib>=1.2.1; extra == 'google'
Provides-Extra: google-genai
Requires-Dist: google-genai; extra == 'google-genai'
Requires-Dist: instructor[google-genai]; extra == 'google-genai'
Provides-Extra: mistralai
Requires-Dist: mistralai==1.5.2; extra == 'mistralai'
